uncle_nelson/__init__.py
uncle_nelson/enums.py
uncle_nelson/mix.py
uncle_nelson/rules.py
uncle_nelson-0.2.0.dist-info/licenses/LICENSE
uncle_nelson-0.2.0.dist-info/METADATA
uncle_nelson-0.2.0.dist-info/WHEEL
uncle_nelson-0.2.0.dist-info/top_level.txt
uncle_nelson-0.2.0.dist-info/RECORD
