Metadata-Version: 2.4
Name: uncle-nelson
Version: 0.2.0
Summary: A small library to calculate mixes for the game Schedule 1
Author: codeofandrin
License: MIT License
Project-URL: Documentation, https://uncle-nelson.readthedocs.io/latest/
Project-URL: Repository, https://github.com/codeofandrin/uncle-nelson
Project-URL: Issues, https://github.com/codeofandrin/uncle-nelson/issues
Classifier: License :: OSI Approved :: MIT License
Classifier: Intended Audience :: Developers
Classifier: Natural Language :: English
Classifier: Operating System :: OS Independent
Classifier: Programming Language :: Python :: 3
Classifier: Programming Language :: Python :: 3.9
Classifier: Programming Language :: Python :: 3.10
Classifier: Programming Language :: Python :: 3.11
Classifier: Programming Language :: Python :: 3.12
Classifier: License :: OSI Approved :: MIT License
Classifier: Operating System :: OS Independent
Classifier: Topic :: Internet
Classifier: Topic :: Software Development :: Libraries
Classifier: Topic :: Software Development :: Libraries :: Python Modules
Classifier: Topic :: Utilities
Classifier: Typing :: Typed
Requires-Python: >=3.9
License-File: LICENSE
Provides-Extra: docs
Requires-Dist: sphinx==7.1.2; extra == "docs"
Requires-Dist: furo; extra == "docs"
Dynamic: license-file
